{"body":{"orderId":"abc","consignee":{"consigneeId":"abc","consigneeName":"悠哈味觉葡萄软糖40g/袋","consigneeTel":"13641882176","consigneeCard":"abc","province":{"regionId":"abc","regionName":"日本温泉酒店特供，天然无硅油不干"},"city":{"regionId":"abc","regionName":"日本温泉酒店特供，天然无硅油不干"},"district":{"regionId":"abc","regionName":"SCOTTIE可莱雅原装进口天然除菌消毒湿巾桶装100抽/桶"},"address":"abc","isDefault":"0"},"delivery":{"deliveryId":"abc","name":"海太蜂蜜黄油薯片60g/包【2包】"},"payment":{"paymentId":"abc","name":"日本温泉酒店特供，天然无硅油不干"},"coupon":{"couponId":"abc","name":"舒洁超厚倍柔小熊系列无香湿纸巾10片*30包","price":"abc","endTime":1488779540},"goods":[{"productId":"abc","name":"海太蜂蜜黄油薯片60g/包【2包】","price":"abc","quantity":"abc","thumbnailPic":"http://img01.rbyair.com/62/f9/a7/7e8ccb51b7806f0daa1241e447e74ccb373.jpg","subTotal":"abc","spec":"abc"},{"productId":"abc","name":"丹麦原装进口，欧洲首批白天鹅标志的班博纸尿裤！","price":"abc","quantity":"abc","thumbnailPic":"http://img01.rbyair.com/0b/ac/5c/187e8bd156c0f211d6a1af7a9e9ec7f57d4.jpg","subTotal":"abc","spec":"abc"},{"productId":"abc","name":"SCOTTIE可莱雅原装进口天然除菌消毒湿巾桶装100抽/桶","price":"abc","quantity":"abc","thumbnailPic":"http://img01.rbyair.com/c5/ee/8a/c14463c531c1d188dc4619878224145398b.jpg","subTotal":"abc","spec":"abc"},{"productId":"abc","name":"悠哈味觉葡萄软糖40g/袋","price":"abc","quantity":"abc","thumbnailPic":"http://img01.rbyair.com/5e/8c/f3/eed57fb28997e9e9afaea65e3a33fead2f6.jpg","subTotal":"abc","spec":"abc"},{"productId":"abc","name":"丹麦原装进口，欧洲首批白天鹅标志的班博纸尿裤！","price":"abc","quantity":"abc","thumbnailPic":"http://img01.rbyair.com/c5/ee/8a/c14463c531c1d188dc4619878224145398b.jpg","subTotal":"abc","spec":"abc"},{"productId":"abc","name":"Shiseido资生堂安耐晒金钻高效防晒喷雾60g","price":"abc","quantity":"abc","thumbnailPic":"http://img01.rbyair.com/6e/d2/c9/ebed888596b4c56dd13b1c7968353a311c2.jpg","subTotal":"abc","spec":"abc"},{"productId":"abc","name":"日本温泉酒店特供，天然无硅油不干","price":"abc","quantity":"abc","thumbnailPic":"http://img01.rbyair.com/5e/8c/f3/eed57fb28997e9e9afaea65e3a33fead2f6.jpg","subTotal":"abc","spec":"abc"},{"productId":"abc","name":"海太蜂蜜黄油薯片60g/包【2包】","price":"abc","quantity":"abc","thumbnailPic":"http://img01.rbyair.com/6e/d2/c9/ebed888596b4c56dd13b1c7968353a311c2.jpg","subTotal":"abc","spec":"abc"},{"productId":"abc","name":"舒洁超厚倍柔小熊系列无香湿纸巾10片*30包","price":"abc","quantity":"abc","thumbnailPic":"http://img01.rbyair.com/cc/ff/08/118de4468cdf05206b15c010261d5c72bdc.jpg","subTotal":"abc","spec":"abc"},{"productId":"abc","name":"海太蜂蜜黄油薯片60g/包【2包】","price":"abc","quantity":"abc","thumbnailPic":"http://img01.rbyair.com/1a/ee/58/7db3226144bc0eb75862b23d3a35c20cfaf.jpg","subTotal":"abc","spec":"abc"}],"total":{"goodsPrice":"abc","discount":"abc","totalTax":"abc","totalFee":"abc","orderPrice":"abc"},"orderSn":"abc","status":"5","addTime":"abc","payTime":"abc","logistic":{"logisticName":"It's","logisticNo":"abc"},"source":"abc"},"code":0,"message":""}