{"body":[{"specId":8456,"specName":"颜色","specValues":[{"productId":2549,"specValue":"紫","imageUrl":"http://m.meigooo.com/category/goods.html","marketable":"1","checked":"0"},{"productId":6488,"specValue":"大","imageUrl":"http://m.meigooo.com/category/goods.html","marketable":"1","checked":"1"}]},{"specId":8409,"specName":"品相","specValues":[{"productId":7269,"specValue":"紫","imageUrl":"http://m.meigooo.com/category/goods.html","marketable":"1","checked":"0"},{"productId":4105,"specValue":"绿","imageUrl":"http://m.meigooo.com/index.html","marketable":"0","checked":"0"}]},{"specId":737,"specName":"颜色","specValues":[{"productId":2562,"specValue":"黄","imageUrl":"http://m.meigooo.com/category/goods.html","marketable":"1","checked":"0"},{"productId":2073,"specValue":"蓝","imageUrl":"http://m.meigooo.com/category/goods.html","marketable":"1","checked":"1"}]},{"specId":6486,"specName":"尺码","specValues":[{"productId":2781,"specValue":"黄","imageUrl":"http://m.meigooo.com/index.html","marketable":"1","checked":"0"},{"productId":832,"specValue":"白","imageUrl":"http://m.meigooo.com/category/goods.html","marketable":"1","checked":"1"},{"productId":3619,"specValue":"绿","imageUrl":"http://m.meigooo.com/category/goods.html","marketable":"1","checked":"1"},{"productId":8660,"specValue":"黑","imageUrl":"http://m.meigooo.com/category/goods.html","marketable":"0","checked":"1"},{"productId":6922,"specValue":"黑","imageUrl":"http://m.meigooo.com/category/goods.html","marketable":"1","checked":"0"},{"productId":6634,"specValue":"黑","imageUrl":"http://m.meigooo.com/index.html","marketable":"0","checked":"1"}]},{"specId":6075,"specName":"品相","specValues":[{"productId":9640,"specValue":"小","imageUrl":"http://m.meigooo.com/index.html","marketable":"0","checked":"1"},{"productId":3432,"specValue":"大","imageUrl":"http://m.meigooo.com/index.html","marketable":"1","checked":"0"},{"productId":2366,"specValue":"小","imageUrl":"http://m.meigooo.com/index.html","marketable":"0","checked":"1"},{"productId":8559,"specValue":"小","imageUrl":"http://m.meigooo.com/category/goods.html","marketable":"1","checked":"1"}]},{"specId":2300,"specName":"品相","specValues":[{"productId":8934,"specValue":"中","imageUrl":"http://m.meigooo.com/index.html","marketable":"0","checked":"1"},{"productId":8189,"specValue":"橙","imageUrl":"http://m.meigooo.com/index.html","marketable":"1","checked":"0"}]},{"specId":4470,"specName":"尺码","specValues":[{"productId":7902,"specValue":"黄","imageUrl":"http://m.meigooo.com/index.html","marketable":"0","checked":"0"},{"productId":5145,"specValue":"黑","imageUrl":"http://m.meigooo.com/index.html","marketable":"1","checked":"1"},{"productId":3260,"specValue":"黄","imageUrl":"http://m.meigooo.com/index.html","marketable":"1","checked":"1"},{"productId":4700,"specValue":"红","imageUrl":"http://m.meigooo.com/category/goods.html","marketable":"0","checked":"0"},{"productId":803,"specValue":"白","imageUrl":"http://m.meigooo.com/index.html","marketable":"1","checked":"0"},{"productId":1861,"specValue":"黑","imageUrl":"http://m.meigooo.com/index.html","marketable":"1","checked":"1"},{"productId":2094,"specValue":"绿","imageUrl":"http://m.meigooo.com/index.html","marketable":"0","checked":"1"},{"productId":7372,"specValue":"大","imageUrl":"http://m.meigooo.com/category/goods.html","marketable":"0","checked":"1"},{"productId":3145,"specValue":"蓝","imageUrl":"http://m.meigooo.com/index.html","marketable":"1","checked":"0"}]},{"specId":2103,"specName":"颜色","specValues":[{"productId":793,"specValue":"绿","imageUrl":"http://m.meigooo.com/index.html","marketable":"0","checked":"1"},{"productId":3170,"specValue":"大","imageUrl":"http://m.meigooo.com/index.html","marketable":"1","checked":"1"},{"productId":6968,"specValue":"中","imageUrl":"http://m.meigooo.com/index.html","marketable":"1","checked":"1"},{"productId":6361,"specValue":"绿","imageUrl":"http://m.meigooo.com/index.html","marketable":"0","checked":"0"},{"productId":1190,"specValue":"白","imageUrl":"http://m.meigooo.com/index.html","marketable":"0","checked":"0"},{"productId":4745,"specValue":"紫","imageUrl":"http://m.meigooo.com/category/goods.html","marketable":"1","checked":"0"},{"productId":2507,"specValue":"橙","imageUrl":"http://m.meigooo.com/index.html","marketable":"0","checked":"1"},{"productId":3567,"specValue":"橙","imageUrl":"http://m.meigooo.com/category/goods.html","marketable":"1","checked":"0"}]},{"specId":7237,"specName":"品相","specValues":[{"productId":9768,"specValue":"红","imageUrl":"http://m.meigooo.com/category/goods.html","marketable":"1","checked":"1"},{"productId":4307,"specValue":"紫","imageUrl":"http://m.meigooo.com/index.html","marketable":"1","checked":"1"},{"productId":823,"specValue":"紫","imageUrl":"http://m.meigooo.com/category/goods.html","marketable":"1","checked":"1"},{"productId":2025,"specValue":"小","imageUrl":"http://m.meigooo.com/category/goods.html","marketable":"0","checked":"0"}]}],"code":0,"message":""}